power_events/__init__.py
power_events/exceptions.py
power_events/py.typed
power_events/resolver.py
power_events/conditions/__init__.py
power_events/conditions/condition.py
power_events/conditions/value.py
power_events-1.2.0.dist-info/METADATA
power_events-1.2.0.dist-info/WHEEL
power_events-1.2.0.dist-info/licenses/LICENSE
power_events-1.2.0.dist-info/RECORD
