Metadata-Version: 2.4
Name: power-events
Version: 1.2.0
Summary: Take control of your event routing.
Project-URL: Homepage, https://pypi.org/project/power-events/
Project-URL: Documentation, https://mletrone.github.io/power-events/
Project-URL: Changelog, https://mletrone.github.io/power-events/changelog
Project-URL: Source, https://github.com/mLetrone/power-events
Project-URL: Tracker, https://github.com/mLetrone/power-events/issues
Author-email: mathieu LETRONE <mathieu.letrone@gmail.com>
License: MIT License
License-File: LICENSE
Classifier: Intended Audience :: Developers
Classifier: License :: OSI Approved :: MIT License
Classifier: Natural Language :: English
Classifier: Operating System :: OS Independent
Classifier: Programming Language :: Python
Classifier: Programming Language :: Python :: 3
Classifier: Programming Language :: Python :: 3 :: Only
Classifier: Programming Language :: Python :: 3.9
Classifier: Programming Language :: Python :: 3.10
Classifier: Programming Language :: Python :: 3.11
Classifier: Programming Language :: Python :: 3.12
Classifier: Programming Language :: Python :: 3.13
Classifier: Programming Language :: Python :: 3.14
Classifier: Programming Language :: Python :: Implementation :: CPython
Classifier: Topic :: Utilities
Classifier: Typing :: Typed
Requires-Python: >=3.9
Requires-Dist: maypy>=1.1.2
